views_tensor_utilities/.DS_Store
views_tensor_utilities/__init__.py
views_tensor_utilities/defaults.py
views_tensor_utilities/mappings.py
views_tensor_utilities/objects.py
views_tensor_utilities-1.1.3.dist-info/METADATA
views_tensor_utilities-1.1.3.dist-info/WHEEL
views_tensor_utilities-1.1.3.dist-info/RECORD
