Metadata-Version: 2.1
Name: views-tensor-utilities
Version: 1.1.3
Summary: Classes and functions for transforming between VIEWS-compliant dfs and tensors
Author: jimdale
Author-email: jimdale@users.noreply.github.com
Requires-Python: >=3.10,<4.0
Classifier: Programming Language :: Python :: 3
Classifier: Programming Language :: Python :: 3.10
Classifier: Programming Language :: Python :: 3.11
Requires-Dist: numpy (>=1.20.0)
Requires-Dist: pandas (>=1.5.0,<2.0.0)
